hf/__init__.py
hf/_config.py
hf/_logging.py
hf/_types.py
hf_py_base-0.2.0.dist-info/METADATA
hf_py_base-0.2.0.dist-info/WHEEL
hf_py_base-0.2.0.dist-info/RECORD
