Metadata-Version: 2.3
Name: hf-py-base
Version: 0.2.0
Summary: 
Author: kuanysh-beisembayev
Author-email: kuanysh.beisembayev@gmail.com
Requires-Python: >=3.12,<4.0
Classifier: Programming Language :: Python :: 3
Classifier: Programming Language :: Python :: 3.12
Classifier: Programming Language :: Python :: 3.13
Requires-Dist: loguru (>=0.7.3,<0.8.0)
Requires-Dist: pydantic-settings (>=2.7.1,<3.0.0)
Requires-Dist: sentry-sdk (>=2.20.0,<3.0.0)
